pulumi_eks/__init__.py
pulumi_eks/_enums.py
pulumi_eks/_inputs.py
pulumi_eks/_utilities.py
pulumi_eks/addon.py
pulumi_eks/cluster.py
pulumi_eks/cluster_creation_role_provider.py
pulumi_eks/managed_node_group.py
pulumi_eks/node_group.py
pulumi_eks/node_group_security_group.py
pulumi_eks/node_group_v2.py
pulumi_eks/outputs.py
pulumi_eks/provider.py
pulumi_eks/pulumi-plugin.json
pulumi_eks/py.typed
pulumi_eks/vpc_cni_addon.py
pulumi_eks-4.0.1.dist-info/METADATA
pulumi_eks-4.0.1.dist-info/WHEEL
pulumi_eks-4.0.1.dist-info/top_level.txt
pulumi_eks-4.0.1.dist-info/RECORD
