Metadata-Version: 2.4
Name: pulumi_eks
Version: 4.0.1
Summary: Pulumi Amazon Web Services (AWS) EKS Components.
License: Apache-2.0
Project-URL: Homepage, https://pulumi.com
Project-URL: Repository, https://github.com/pulumi/pulumi-eks
Keywords: pulumi,aws,eks
Requires-Python: >=3.9
Requires-Dist: parver>=0.2.1
Requires-Dist: pulumi<4.0.0,>=3.165.0
Requires-Dist: pulumi-aws<8.0.0,>=7.1.0
Requires-Dist: pulumi-kubernetes<5.0.0,>=4.19.0
Requires-Dist: semver>=2.8.1
Requires-Dist: typing-extensions<5,>=4.11; python_version < "3.11"
